pd_dwi/__init__.py
pd_dwi/config/__init__.py
pd_dwi/config/config.py
pd_dwi/config/samples/F.yaml
pd_dwi/config/samples/adc0100.yaml
pd_dwi/config/samples/adc0100600800.yaml
pd_dwi/config/samples/adc0100_F.yaml
pd_dwi/config/samples/adc100600800.yaml
pd_dwi/config/utils.py
pd_dwi/dataset.py
pd_dwi/dcm_utils/__init__.py
pd_dwi/dcm_utils/reader.py
pd_dwi/dcm_utils/tags.py
pd_dwi/dcm_utils/writer.py
pd_dwi/feature_selection/__init__.py
pd_dwi/feature_selection/select_k_best.py
pd_dwi/model.py
pd_dwi/models/F.pkl
pd_dwi/models/__init__.py
pd_dwi/models/adc0100.pkl
pd_dwi/models/adc0100600800.pkl
pd_dwi/models/adc0100_F.pkl
pd_dwi/models/adc100600800.pkl
pd_dwi/models/registry.json
pd_dwi/preprocessing/__init__.py
pd_dwi/preprocessing/adc.py
pd_dwi/preprocessing/column_transformer.py
pd_dwi/preprocessing/transformers/__init__.py
pd_dwi/preprocessing/transformers/hormone_receptor_encoder.py
pd_dwi/preprocessing/transformers/radiomics_encoder.py
pd_dwi/preprocessing/transformers/sbr_grade_encoder.py
pd_dwi/scripts/__init__.py
pd_dwi/scripts/adc_preprocess_command.py
pd_dwi/scripts/cli.py
pd_dwi/scripts/list_command.py
pd_dwi/scripts/predict_command.py
pd_dwi/scripts/score_command.py
pd_dwi/scripts/train_command.py
pd_dwi/training_utils.py
pd_dwi-1.1.4.dist-info/entry_points.txt
pd_dwi-1.1.4.dist-info/LICENSE.txt
pd_dwi-1.1.4.dist-info/WHEEL
pd_dwi-1.1.4.dist-info/METADATA
pd_dwi-1.1.4.dist-info/RECORD
