Metadata-Version: 2.1
Name: pd-dwi
Version: 1.1.4
Summary: Physiologically-Decomposed Diffusion-Weighted MRI machine-learning model for predicting response to neoadjuvant chemotherapy in invasive breast cancer
Home-page: https://tcml-bme.github.io/
Author: Maya Gilad
Author-email: ms.maya.gilad@gmail.com
Requires-Python: >=3.8.1,<3.9
Classifier: Development Status :: 3 - Alpha
Classifier: Environment :: Console
Classifier: Intended Audience :: Developers
Classifier: Intended Audience :: Science/Research
Classifier: License :: OSI Approved :: BSD License
Classifier: Operating System :: OS Independent
Classifier: Programming Language :: Python :: 3
Classifier: Programming Language :: Python :: 3.8
Classifier: Topic :: Scientific/Engineering :: Bio-Informatics
Provides-Extra: preprocessing
Requires-Dist: Cython (>=0.29.30,<0.30.0)
Requires-Dist: PyYAML (>=6.0,<7.0)
Requires-Dist: StrEnum (>=0.4.15,<0.5.0); python_version < "3.11"
Requires-Dist: click (>=8.1.7,<9.0.0)
Requires-Dist: jsonschema (>=4.6.0,<5.0.0)
Requires-Dist: numpy (>=1.22.0,<2.0.0)
Requires-Dist: pandas (>=1.4.3,<2.0.0)
Requires-Dist: pydantic (>=2.6.4,<3.0.0)
Requires-Dist: pydantic-yaml (>=1.2.1,<2.0.0)
Requires-Dist: pydicom (>=2.4.4,<3.0.0); extra == "preprocessing"
Requires-Dist: pyradiomics (>=3.0.1,<4.0.0)
Requires-Dist: scikit-learn (>=1.0.2,<2.0.0)
Requires-Dist: xgboost (>=1.6.1,<2.0.0)
Project-URL: Documentation, https://pd-dwi.readthedocs.io/en/stable/
Project-URL: Repository, https://github.com/TechnionComputationalMRILab/PD-DWI
